README
setup.py
upicasa.py
upicasa.egg-info/PKG-INFO
upicasa.egg-info/SOURCES.txt
upicasa.egg-info/dependency_links.txt
upicasa.egg-info/entry_points.txt
upicasa.egg-info/requires.txt
upicasa.egg-info/top_level.txt