Metadata-Version: 1.0
Name: upicasa
Version: 0.2
Summary: A command line uploader for PicasaWeb
Home-page: UNKNOWN
Author: Albertas Agejevas
Author-email: alga@pov.lt
License: UNKNOWN
Keywords: picasaweb google picasa upload
Platform: UNKNOWN
Classifier: Development Status :: 4 - Beta
Classifier: Environment :: Console
Classifier: Intended Audience :: End Users/Desktop
Classifier: License :: OSI Approved :: GNU General Public License (GPL)
Classifier: Programming Language :: Python
Classifier: Natural Language :: English
Classifier: Operating System :: OS Independent
Classifier: Topic :: Internet :: WWW/HTTP :: Site Management
Classifier: Topic :: Multimedia :: Graphics
Classifier: Topic :: Utilities
